SCPLibrary/__init__.py
SCPLibrary/library.py
robotframework_scpcompat-0.1.0.dist-info/DESCRIPTION.rst
robotframework_scpcompat-0.1.0.dist-info/LICENSE.txt
robotframework_scpcompat-0.1.0.dist-info/METADATA
robotframework_scpcompat-0.1.0.dist-info/RECORD
robotframework_scpcompat-0.1.0.dist-info/WHEEL
robotframework_scpcompat-0.1.0.dist-info/metadata.json
robotframework_scpcompat-0.1.0.dist-info/top_level.txt
robotframework_scpcompat-0.1.0.dist-info/zip-safe
