Metadata-Version: 2.0
Name: robotframework-scpcompat
Version: 0.1.0
Summary: RobotFramework library for Secure Copy file transfers (SCP) that
Requires-Dist: robotframework-sshlibrary
Requires-Dist: scp
